setup.cfg
setup.py
bin/glpi-cli
glpi_cli.egg-info/PKG-INFO
glpi_cli.egg-info/SOURCES.txt
glpi_cli.egg-info/dependency_links.txt
glpi_cli.egg-info/requires.txt
glpi_cli.egg-info/top_level.txt
glpicli/__init__.py
glpicli/glpicli.py
glpicli/version.py