Metadata-Version: 1.1
Name: glpi-cli
Version: 0.2.0
Summary: GLPI Command Line Interface
Home-page: https://github.com/mtulio/glpi-cli
Author: Marco Tulio R Braga
Author-email: braga@mtulio.eng.br
License: Apache-2.0
Download-URL: https://github.com/mtulio/glpi-cli/archive/0.2.0.tar.gz
Keywords: GLPI,CLI
Platform: UNKNOWN
